couchdol/__init__.py
couchdol/tests/__init__.py
couchdol/tests/test_simple.py
couchdol-0.0.2.dist-info/LICENSE
couchdol-0.0.2.dist-info/METADATA
couchdol-0.0.2.dist-info/WHEEL
couchdol-0.0.2.dist-info/top_level.txt
couchdol-0.0.2.dist-info/RECORD
