Metadata-Version: 2.1
Name: couchdol
Version: 0.0.2
Summary: couchdb with a simple (dict-like or list-like) interface
Home-page: https://github.com/i2mint/couchdol
Author: OtoSense
License: apache-2.0
Keywords: couchdb,data access
Platform: any
Requires-Dist: dol
Requires-Dist: couchdb
